drasyl/__init__.py
drasyl/libdrasyl.py
drasyl/version.py
drasyl/libdrasyl/libdrasyl.dylib
drasyl-0.12.0.dist-info/licenses/LICENSE
drasyl-0.12.0.dist-info/METADATA
drasyl-0.12.0.dist-info/WHEEL
drasyl-0.12.0.dist-info/top_level.txt
drasyl-0.12.0.dist-info/RECORD
