Metadata-Version: 2.4
Name: drasyl
Version: 0.12.0
Summary: drasyl is a general-purpose overlay network framework for rapid development of distributed P2P applications
Author-email: Heiko Bornholdt <bornholdt@informatik.uni-hamburg.de>, Kevin Röbert <kevin.roebert@uni-hamburg.de>
License: Copyright (c) 2020-2022 Heiko Bornholdt and Kevin Röbert
Project-URL: Documentation, https://docs.drasyl.org/
Project-URL: Source, https://github.com/drasyl/drasyl
Project-URL: Changelog, https://github.com/drasyl/drasyl/blob/master/CHANGELOG.md
Project-URL: Homepage, https://drasyl.org
Project-URL: Issue Tracker, https://github.com/drasyl/drasyl/issues
Classifier: Development Status :: 5 - Production/Stable
Classifier: Topic :: Communications
Classifier: Topic :: Internet
Classifier: Topic :: Scientific/Engineering
Classifier: Topic :: Security :: Cryptography
Classifier: Topic :: System :: Networking
Classifier: Intended Audience :: Developers
Classifier: Intended Audience :: Information Technology
Classifier: Intended Audience :: Science/Research
Classifier: Intended Audience :: System Administrators
Classifier: License :: OSI Approved :: MIT License
Classifier: Programming Language :: C
Classifier: Programming Language :: Python :: 3
Classifier: Operating System :: MacOS
Classifier: Operating System :: Microsoft :: Windows
Classifier: Operating System :: POSIX :: Linux
Classifier: Programming Language :: C
Classifier: Programming Language :: Python
Requires-Python: >=3.7
License-File: LICENSE
Dynamic: license-file
